  {
  	"type": "FeatureCollection",
  	"features": [{
  			"type": "Feature",
  			"geometry": {
  				"type": "Point",
  				"coordinates": [-82.52479, 27.96065]
  			},
  			"properties": {
  				"phoneFormatted": "(813) 856-5001",
  				"phone": "+18138565001",
  				"address": "7320 East Fletcher Ave",
  				"city": "Tampa, FL",
  				"country": "United States",
  				"crossStreet": "",
  				"postalCode": "33637",
  				"state": "1"
  			}

  		}, {
  			"type": "Feature",
  			"geometry": {
  				"type": "Point",
  				"coordinates": [-81.36881,
  					28.53797,
  					0
  				]
  			},
  			"properties": {
  				"phoneFormatted": "(407) 857-9458",
  				"phone": "+14078579458",
  				"address": "1802 Alafaya Trail",
  				"city": "Orlando, FL",
  				"country": "United States",
  				"crossStreet": "",
  				"postalCode": "32826",
  				"state": "2"
  			}

  		}, {
  			"type": "Feature",
  			"geometry": {
  				"type": "Point",
  				"coordinates": [-80.14749,
  					26.71216,
  					0
  				]
  			},
  			"properties": {
  				"phoneFormatted": "(561) 412-1825",
  				"phone": "+15614121825",
  				"address": "2054 Vista Parkway",
  				"city": "West Palm Beach, FL",
  				"country": "United States",
  				"crossStreet": "",
  				"postalCode": "33411",
  				"state": "3"
  			}

  		}, {
  			"type": "Feature",
  			"geometry": {
  				"type": "Point",
  				"coordinates": [-81.66353,
  					30.31636,
  					0
  				]
  			},
  			"properties": {
  				"phoneFormatted": "(904) 770-5005",
  				"phone": "+19047705005",
  				"address": "841 Prudential Dr., 12th Floor",
  				"city": "Jacksonville, FL",
  				"country": "United States",
  				"crossStreet": "",
  				"postalCode": "32207",
  				"state": "4"
  			}


  		},

  		{









  		}
  	]
  }
